alohomora/__init__.py
alohomora/keys.py
alohomora/main.py
alohomora/req.py
alohomora/saml.py
alohomora-3.1.1.dist-info/LICENSE
alohomora-3.1.1.dist-info/METADATA
alohomora-3.1.1.dist-info/WHEEL
alohomora-3.1.1.dist-info/entry_points.txt
alohomora-3.1.1.dist-info/top_level.txt
alohomora-3.1.1.dist-info/RECORD
