Metadata-Version: 2.1
Name: alohomora
Version: 3.1.1
Summary: Get AWS API keys for a SAML-federated identity
Home-page: https://github.com/Viasat/alohomora
Author: Viasat
Author-email: vice-support@viasat.com
License: (c) 2024 Viasat, Inc. See the LICENSE file for more details.
License-File: LICENSE
Requires-Dist: boto3 >=1.3.1
Requires-Dist: beautifulsoup4 >=4.5.1
Requires-Dist: requests >=2.11.1
Provides-Extra: fido2
Requires-Dist: fido2 ==0.9.3 ; extra == 'fido2'
